bunnypy/__init__.py
bunnypy/bunnypy.py
bunnypy/asset/error.html
BunnyPy-0.3.3.dist-info/LICENSE
BunnyPy-0.3.3.dist-info/METADATA
BunnyPy-0.3.3.dist-info/WHEEL
BunnyPy-0.3.3.dist-info/top_level.txt
BunnyPy-0.3.3.dist-info/RECORD
