Metadata-Version: 2.1
Name: BunnyPy
Version: 0.3.3
Summary: Lightweight Python Web Framework
Home-page: https://github.com/ivanlulyf/bunnypy
Author: IvanLuLyf
Author-email: me@ivanlu.cn
License: MIT
Platform: any
Classifier: Operating System :: OS Independent
Classifier: Intended Audience :: Developers
Classifier: License :: OSI Approved :: MIT License
Classifier: Topic :: Internet :: WWW/HTTP :: HTTP Servers
Classifier: Topic :: Internet :: WWW/HTTP :: WSGI
Classifier: Topic :: Software Development :: Libraries :: Application Frameworks
Classifier: Programming Language :: Python :: 3.9
Classifier: Programming Language :: Python :: 3.10
Classifier: Programming Language :: Python :: 3.11
License-File: LICENSE
